square_matrix_converter/__init__.py
square_matrix_converter/convert_matrix.py
square_matrix_converter/convert_square_matrix.py
square_matrix_converter/parse_matrix.py
tests/__init__.py
tests/test_convert_matrix.py
tests/test_convert_square_matrix.py
tests/test_parse_matrix.py
square_matrix_converter-0.1.0.dist-info/LICENSE
square_matrix_converter-0.1.0.dist-info/METADATA
square_matrix_converter-0.1.0.dist-info/WHEEL
square_matrix_converter-0.1.0.dist-info/top_level.txt
square_matrix_converter-0.1.0.dist-info/RECORD
